{"response_data": {"get": "fixtures", "parameters": {"id": "1490061"}, "errors": [], "results": 1, "paging": {"current": 1, "total": 1}, "response": [{"fixture": {"id": 1490061, "referee": null, "timezone": "UTC", "date": "2026-06-02T16:00:00+00:00", "timestamp": 1780416000, "periods": {"first": 1780416000, "second": 1780419600}, "venue": {"id": null, "name": "Sportovni areal Viktoria", "city": null}, "status": {"long": "Match Finished", "short": "FT", "elapsed": 90, "extra": 1}}, "league": {"id": 351, "name": "4. liga - Divizie B", "country": "Czech-Republic", "logo": "https://media.api-sports.io/football/leagues/351.png", "flag": "https://media.api-sports.io/flags/cz.svg", "season": 2025, "round": "Division B - 24", "standings": true}, "teams": {"home": {"id": 7317, "name": "Mari\u00e1nsk\u00e9 L\u00e1zn\u011b", "logo": "https://media.api-sports.io/football/teams/7317.png", "winner": false}, "away": {"id": 7306, "name": "Karlovy Vary", "logo": "https://media.api-sports.io/football/teams/7306.png", "winner": true}}, "goals": {"home": 1, "away": 4}, "score": {"halftime": {"home": 1, "away": 3}, "fulltime": {"home": 1, "away": 4}, "extratime": {"home": null, "away": null}, "penalty": {"home": null, "away": null}}, "events": [], "lineups": [], "statistics": [], "players": []}]}, "timestamp": "2026-06-02T19:31:04.692933"}