{"response_data": {"get": "fixtures", "parameters": {"id": "1515745"}, "errors": [], "results": 1, "paging": {"current": 1, "total": 1}, "response": [{"fixture": {"id": 1515745, "referee": null, "timezone": "UTC", "date": "2026-06-06T11:00:00+00:00", "timestamp": 1780743600, "periods": {"first": 1780743600, "second": 1780747200}, "venue": {"id": null, "name": null, "city": null}, "status": {"long": "Match Finished", "short": "FT", "elapsed": 90, "extra": null}}, "league": {"id": 594, "name": "Division 2 - Norrland", "country": "Sweden", "logo": "https://media.api-sports.io/football/leagues/594.png", "flag": "https://media.api-sports.io/flags/se.svg", "season": 2026, "round": "Norrland - 10", "standings": true}, "teams": {"home": {"id": 6681, "name": "IFK \u00d6stersund", "logo": "https://media.api-sports.io/football/teams/6681.png", "winner": null}, "away": {"id": 12586, "name": "Friska Viljor", "logo": "https://media.api-sports.io/football/teams/12586.png", "winner": null}}, "goals": {"home": 0, "away": 0}, "score": {"halftime": {"home": 0, "away": 0}, "fulltime": {"home": 0, "away": 0}, "extratime": {"home": null, "away": null}, "penalty": {"home": null, "away": null}}, "events": [], "lineups": [], "statistics": [], "players": []}]}, "timestamp": "2026-06-06T14:22:46.695178"}