{"response_data": {"get": "fixtures", "parameters": {"team": "18686", "last": "10", "status": "FT", "season": "2026"}, "errors": [], "results": 10, "paging": {"current": 1, "total": 1}, "response": [{"fixture": {"id": 1512443, "referee": null, "timezone": "UTC", "date": "2026-06-03T18:00:00+00:00", "timestamp": 1780509600, "periods": {"first": 1780509600, "second": 1780513200}, "venue": {"id": null, "name": "Victor Legrotaglie", "city": "Mendoza"}, "status": {"long": "Match Finished", "short": "FT", "elapsed": 90, "extra": 4}}, "league": {"id": 906, "name": "Reserve League", "country": "Argentina", "logo": "https://media.api-sports.io/football/leagues/906.png", "flag": "https://media.api-sports.io/flags/ar.svg", "season": 2026, "round": "Regular Season - 16", "standings": true}, "teams": {"home": {"id": 27272, "name": "Gimnasia Mendoza 2", "logo": "https://media.api-sports.io/football/teams/27272.png", "winner": null}, "away": {"id": 18686, "name": "Gimnasia La Plata Res.", "logo": "https://media.api-sports.io/football/teams/18686.png", "winner": null}}, "goals": {"home": 0, "away": 0}, "score": {"halftime": {"home": 0, "away": 0}, "fulltime": {"home": 0, "away": 0}, "extratime": {"home": null, "away": null}, "penalty": {"home": null, "away": null}}}, {"fixture": {"id": 1512424, "referee": null, "timezone": "UTC", "date": "2026-05-28T18:00:00+00:00", "timestamp": 1779991200, "periods": {"first": 1779991200, "second": 1779994800}, "venue": {"id": null, "name": null, "city": null}, "status": {"long": "Match Finished", "short": "FT", "elapsed": 90, "extra": 6}}, "league": {"id": 906, "name": "Reserve League", "country": "Argentina", "logo": "https://media.api-sports.io/football/leagues/906.png", "flag": "https://media.api-sports.io/flags/ar.svg", "season": 2026, "round": "Regular Season - 15", "standings": true}, "teams": {"home": {"id": 18686, "name": "Gimnasia La Plata Res.", "logo": "https://media.api-sports.io/football/teams/18686.png", "winner": null}, "away": {"id": 18680, "name": "Barracas Central Res.", "logo": "https://media.api-sports.io/football/teams/18680.png", "winner": null}}, "goals": {"home": 0, "away": 0}, "score": {"halftime": {"home": 0, "away": 0}, "fulltime": {"home": 0, "away": 0}, "extratime": {"home": null, "away": null}, "penalty": {"home": null, "away": null}}}, {"fixture": {"id": 1512414, "referee": null, "timezone": "UTC", "date": "2026-05-21T22:00:00+00:00", "timestamp": 1779400800, "periods": {"first": 1779400800, "second": 1779404400}, "venue": {"id": null, "name": null, "city": null}, "status": {"long": "Match Finished", "short": "FT", "elapsed": 90, "extra": 8}}, "league": {"id": 906, "name": "Reserve League", "country": "Argentina", "logo": "https://media.api-sports.io/football/leagues/906.png", "flag": "https://media.api-sports.io/flags/ar.svg", "season": 2026, "round": "Regular Season - 14", "standings": true}, "teams": {"home": {"id": 18699, "name": "Talleres C\u00f3rdoba Res.", "logo": "https://media.api-sports.io/football/teams/18699.png", "winner": false}, "away": {"id": 18686, "name": "Gimnasia La Plata Res.", "logo": "https://media.api-sports.io/football/teams/18686.png", "winner": true}}, "goals": {"home": 1, "away": 2}, "score": {"halftime": {"home": 1, "away": 1}, "fulltime": {"home": 1, "away": 2}, "extratime": {"home": null, "away": null}, "penalty": {"home": null, "away": null}}}, {"fixture": {"id": 1512389, "referee": null, "timezone": "UTC", "date": "2026-05-12T18:00:00+00:00", "timestamp": 1778608800, "periods": {"first": 1778608800, "second": 1778612400}, "venue": {"id": null, "name": null, "city": null}, "status": {"long": "Match Finished", "short": "FT", "elapsed": 90, "extra": 4}}, "league": {"id": 906, "name": "Reserve League", "country": "Argentina", "logo": "https://media.api-sports.io/football/leagues/906.png", "flag": "https://media.api-sports.io/flags/ar.svg", "season": 2026, "round": "Regular Season - 13", "standings": true}, "teams": {"home": {"id": 18686, "name": "Gimnasia La Plata Res.", "logo": "https://media.api-sports.io/football/teams/18686.png", "winner": true}, "away": {"id": 18679, "name": "Banfield Res.", "logo": "https://media.api-sports.io/football/teams/18679.png", "winner": false}}, "goals": {"home": 2, "away": 0}, "score": {"halftime": {"home": 1, "away": 0}, "fulltime": {"home": 2, "away": 0}, "extratime": {"home": null, "away": null}, "penalty": {"home": null, "away": null}}}, {"fixture": {"id": 1512375, "referee": null, "timezone": "UTC", "date": "2026-05-06T18:00:00+00:00", "timestamp": 1778090400, "periods": {"first": 1778090400, "second": 1778094000}, "venue": {"id": null, "name": null, "city": null}, "status": {"long": "Match Finished", "short": "FT", "elapsed": 90, "extra": 6}}, "league": {"id": 906, "name": "Reserve League", "country": "Argentina", "logo": "https://media.api-sports.io/football/leagues/906.png", "flag": "https://media.api-sports.io/flags/ar.svg", "season": 2026, "round": "Regular Season - 12", "standings": true}, "teams": {"home": {"id": 18696, "name": "Rosario Central Res.", "logo": "https://media.api-sports.io/football/teams/18696.png", "winner": null}, "away": {"id": 18686, "name": "Gimnasia La Plata Res.", "logo": "https://media.api-sports.io/football/teams/18686.png", "winner": null}}, "goals": {"home": 0, "away": 0}, "score": {"halftime": {"home": 0, "away": 0}, "fulltime": {"home": 0, "away": 0}, "extratime": {"home": null, "away": null}, "penalty": {"home": null, "away": null}}}, {"fixture": {"id": 1512354, "referee": null, "timezone": "UTC", "date": "2026-04-28T18:00:00+00:00", "timestamp": 1777399200, "periods": {"first": 1777399200, "second": 1777402800}, "venue": {"id": null, "name": null, "city": null}, "status": {"long": "Match Finished", "short": "FT", "elapsed": 90, "extra": 5}}, "league": {"id": 906, "name": "Reserve League", "country": "Argentina", "logo": "https://media.api-sports.io/football/leagues/906.png", "flag": "https://media.api-sports.io/flags/ar.svg", "season": 2026, "round": "Regular Season - 11", "standings": true}, "teams": {"home": {"id": 18686, "name": "Gimnasia La Plata Res.", "logo": "https://media.api-sports.io/football/teams/18686.png", "winner": false}, "away": {"id": 18700, "name": "Tigre Res.", "logo": "https://media.api-sports.io/football/teams/18700.png", "winner": true}}, "goals": {"home": 1, "away": 2}, "score": {"halftime": {"home": 0, "away": 0}, "fulltime": {"home": 1, "away": 2}, "extratime": {"home": null, "away": null}, "penalty": {"home": null, "away": null}}}, {"fixture": {"id": 1512332, "referee": null, "timezone": "UTC", "date": "2026-04-22T17:00:00+00:00", "timestamp": 1776877200, "periods": {"first": 1776877200, "second": 1776880800}, "venue": {"id": null, "name": null, "city": null}, "status": {"long": "Match Finished", "short": "FT", "elapsed": 90, "extra": 5}}, "league": {"id": 906, "name": "Reserve League", "country": "Argentina", "logo": "https://media.api-sports.io/football/leagues/906.png", "flag": "https://media.api-sports.io/flags/ar.svg", "season": 2026, "round": "Regular Season - 10", "standings": true}, "teams": {"home": {"id": 18685, "name": "Estudiantes La Plata Res", "logo": "https://media.api-sports.io/football/teams/18685.png", "winner": true}, "away": {"id": 18686, "name": "Gimnasia La Plata Res.", "logo": "https://media.api-sports.io/football/teams/18686.png", "winner": false}}, "goals": {"home": 1, "away": 0}, "score": {"halftime": {"home": 1, "away": 0}, "fulltime": {"home": 1, "away": 0}, "extratime": {"home": null, "away": null}, "penalty": {"home": null, "away": null}}}, {"fixture": {"id": 1512322, "referee": null, "timezone": "UTC", "date": "2026-04-14T16:30:00+00:00", "timestamp": 1776184200, "periods": {"first": 1776184200, "second": 1776187800}, "venue": {"id": null, "name": null, "city": null}, "status": {"long": "Match Finished", "short": "FT", "elapsed": 90, "extra": 3}}, "league": {"id": 906, "name": "Reserve League", "country": "Argentina", "logo": "https://media.api-sports.io/football/leagues/906.png", "flag": "https://media.api-sports.io/flags/ar.svg", "season": 2026, "round": "Regular Season - 9", "standings": true}, "teams": {"home": {"id": 18697, "name": "San Lorenzo Res.", "logo": "https://media.api-sports.io/football/teams/18697.png", "winner": false}, "away": {"id": 18686, "name": "Gimnasia La Plata Res.", "logo": "https://media.api-sports.io/football/teams/18686.png", "winner": true}}, "goals": {"home": 0, "away": 2}, "score": {"halftime": {"home": 0, "away": 1}, "fulltime": {"home": 0, "away": 2}, "extratime": {"home": null, "away": null}, "penalty": {"home": null, "away": null}}}, {"fixture": {"id": 1512300, "referee": null, "timezone": "UTC", "date": "2026-04-08T18:00:00+00:00", "timestamp": 1775671200, "periods": {"first": 1775671200, "second": 1775674800}, "venue": {"id": null, "name": null, "city": null}, "status": {"long": "Match Finished", "short": "FT", "elapsed": 90, "extra": 4}}, "league": {"id": 906, "name": "Reserve League", "country": "Argentina", "logo": "https://media.api-sports.io/football/leagues/906.png", "flag": "https://media.api-sports.io/flags/ar.svg", "season": 2026, "round": "Regular Season - 8", "standings": true}, "teams": {"home": {"id": 18686, "name": "Gimnasia La Plata Res.", "logo": "https://media.api-sports.io/football/teams/18686.png", "winner": false}, "away": {"id": 18702, "name": "V\u00e9lez S\u00e1rsfield Res.", "logo": "https://media.api-sports.io/football/teams/18702.png", "winner": true}}, "goals": {"home": 0, "away": 1}, "score": {"halftime": {"home": 0, "away": 1}, "fulltime": {"home": 0, "away": 1}, "extratime": {"home": null, "away": null}, "penalty": {"home": null, "away": null}}}, {"fixture": {"id": 1512284, "referee": null, "timezone": "UTC", "date": "2026-04-02T21:00:00+00:00", "timestamp": 1775163600, "periods": {"first": 1775163600, "second": 1775167200}, "venue": {"id": null, "name": null, "city": null}, "status": {"long": "Match Finished", "short": "FT", "elapsed": 90, "extra": 5}}, "league": {"id": 906, "name": "Reserve League", "country": "Argentina", "logo": "https://media.api-sports.io/football/leagues/906.png", "flag": "https://media.api-sports.io/flags/ar.svg", "season": 2026, "round": "Regular Season - 7", "standings": true}, "teams": {"home": {"id": 18695, "name": "River Plate Res.", "logo": "https://media.api-sports.io/football/teams/18695.png", "winner": false}, "away": {"id": 18686, "name": "Gimnasia La Plata Res.", "logo": "https://media.api-sports.io/football/teams/18686.png", "winner": true}}, "goals": {"home": 0, "away": 3}, "score": {"halftime": {"home": 0, "away": 0}, "fulltime": {"home": 0, "away": 3}, "extratime": {"home": null, "away": null}, "penalty": {"home": null, "away": null}}}]}, "timestamp": "2026-06-08T19:38:50.800966"}