{"response_data": {"get": "fixtures", "parameters": {"id": "1548327"}, "errors": [], "results": 1, "paging": {"current": 1, "total": 1}, "response": [{"fixture": {"id": 1548327, "referee": "E. El Hanafi", "timezone": "UTC", "date": "2026-06-08T16:00:00+00:00", "timestamp": 1780934400, "periods": {"first": 1780934400, "second": 1780938000}, "venue": {"id": null, "name": "Stade Prince Moulay Hassan", "city": "Rabat"}, "status": {"long": "Match Finished", "short": "FT", "elapsed": 90, "extra": 6}}, "league": {"id": 200, "name": "Botola Pro", "country": "Morocco", "logo": "https://media.api-sports.io/football/leagues/200.png", "flag": "https://media.api-sports.io/flags/ma.svg", "season": 2025, "round": "Regular Season - 23", "standings": true}, "teams": {"home": {"id": 977, "name": "FUS Rabat", "logo": "https://media.api-sports.io/football/teams/977.png", "winner": null}, "away": {"id": 964, "name": "Difaa EL Jadida", "logo": "https://media.api-sports.io/football/teams/964.png", "winner": null}}, "goals": {"home": 0, "away": 0}, "score": {"halftime": {"home": 0, "away": 0}, "fulltime": {"home": 0, "away": 0}, "extratime": {"home": null, "away": null}, "penalty": {"home": null, "away": null}}, "events": [{"time": {"elapsed": 23, "extra": null}, "team": {"id": 964, "name": "Difaa EL Jadida", "logo": "https://media.api-sports.io/football/teams/964.png"}, "player": {"id": 271786, "name": "Y. Michte"}, "assist": {"id": null, "name": null}, "type": "Card", "detail": "Yellow Card", "comments": null}, {"time": {"elapsed": 59, "extra": null}, "team": {"id": 977, "name": "FUS Rabat", "logo": "https://media.api-sports.io/football/teams/977.png"}, "player": {"id": 36694, "name": "L. Diakite"}, "assist": {"id": null, "name": null}, "type": "Card", "detail": "Yellow Card", "comments": null}, {"time": {"elapsed": 62, "extra": null}, "team": {"id": 964, "name": "Difaa EL Jadida", "logo": "https://media.api-sports.io/football/teams/964.png"}, "player": {"id": 535210, "name": "M. Mouchtanim"}, "assist": {"id": null, "name": null}, "type": "Card", "detail": "Yellow Card", "comments": null}, {"time": {"elapsed": 63, "extra": null}, "team": {"id": 977, "name": "FUS Rabat", "logo": "https://media.api-sports.io/football/teams/977.png"}, "player": {"id": 195071, "name": "O. Soukhane"}, "assist": {"id": null, "name": null}, "type": "Card", "detail": "Yellow Card", "comments": null}, {"time": {"elapsed": 65, "extra": null}, "team": {"id": 964, "name": "Difaa EL Jadida", "logo": "https://media.api-sports.io/football/teams/964.png"}, "player": {"id": 535208, "name": "A. Ennakouss"}, "assist": {"id": 535207, "name": "R. Da Costa"}, "type": "subst", "detail": "Substitution 1", "comments": null}, {"time": {"elapsed": 66, "extra": null}, "team": {"id": 964, "name": "Difaa EL Jadida", "logo": "https://media.api-sports.io/football/teams/964.png"}, "player": {"id": 535210, "name": "M. Mouchtanim"}, "assist": {"id": 535211, "name": "A. Idrissi"}, "type": "subst", "detail": "Substitution 2", "comments": null}, {"time": {"elapsed": 67, "extra": null}, "team": {"id": 977, "name": "FUS Rabat", "logo": "https://media.api-sports.io/football/teams/977.png"}, "player": {"id": 184004, "name": "A. El Harrak"}, "assist": {"id": 338553, "name": "C. Faidi"}, "type": "subst", "detail": "Substitution 1", "comments": null}, {"time": {"elapsed": 67, "extra": null}, "team": {"id": 977, "name": "FUS Rabat", "logo": "https://media.api-sports.io/football/teams/977.png"}, "player": {"id": 36694, "name": "L. Diakite"}, "assist": {"id": 535235, "name": "A. Gitego"}, "type": "subst", "detail": "Substitution 2", "comments": null}, {"time": {"elapsed": 69, "extra": null}, "team": {"id": 977, "name": "FUS Rabat", "logo": "https://media.api-sports.io/football/teams/977.png"}, "player": {"id": 338553, "name": "C. Faidi"}, "assist": {"id": null, "name": null}, "type": "Card", "detail": "Yellow Card", "comments": null}, {"time": {"elapsed": 73, "extra": null}, "team": {"id": 964, "name": "Difaa EL Jadida", "logo": "https://media.api-sports.io/football/teams/964.png"}, "player": {"id": 535238, "name": "Z. Oubraim"}, "assist": {"id": 590903, "name": "O. Benchchaoui"}, "type": "subst", "detail": "Substitution 3", "comments": null}, {"time": {"elapsed": 76, "extra": null}, "team": {"id": 977, "name": "FUS Rabat", "logo": "https://media.api-sports.io/football/teams/977.png"}, "player": {"id": 195070, "name": "A. Souane"}, "assist": {"id": 294298, "name": "I. Moutaraji"}, "type": "subst", "detail": "Substitution 3", "comments": null}, {"time": {"elapsed": 83, "extra": null}, "team": {"id": 977, "name": "FUS Rabat", "logo": "https://media.api-sports.io/football/teams/977.png"}, "player": {"id": 195071, "name": "O. Soukhane"}, "assist": {"id": 303520, "name": "O. Raoui"}, "type": "subst", "detail": "Substitution 4", "comments": null}, {"time": {"elapsed": 87, "extra": null}, "team": {"id": 964, "name": "Difaa EL Jadida", "logo": "https://media.api-sports.io/football/teams/964.png"}, "player": {"id": 535207, "name": "R. Da Costa"}, "assist": {"id": 568697, "name": "I. Sabik"}, "type": "subst", "detail": "Substitution 4", "comments": null}, {"time": {"elapsed": 87, "extra": null}, "team": {"id": 964, "name": "Difaa EL Jadida", "logo": "https://media.api-sports.io/football/teams/964.png"}, "player": {"id": 535209, "name": "A. Ziani"}, "assist": {"id": 581417, "name": "A. Mostakime"}, "type": "subst", "detail": "Substitution 5", "comments": null}], "lineups": [{"team": {"id": 977, "name": "FUS Rabat", "logo": "https://media.api-sports.io/football/teams/977.png", "colors": {"player": {"primary": "ffffff", "number": "dd0000", "border": "ffffff"}, "goalkeeper": {"primary": "cc6699", "number": "ffffff", "border": "cc6699"}}}, "formation": "4-2-3-1", "startXI": [{"player": {"id": 36655, "name": "Ayoub Lakred", "number": 36, "pos": "G", "grid": "1:1"}}, {"player": {"id": 152424, "name": "Houdaifa El Mahasni", "number": 22, "pos": "D", "grid": "2:4"}}, {"player": {"id": 119553, "name": "Fernando Chamboco", "number": 40, "pos": "D", "grid": "2:3"}}, {"player": {"id": 639638, "name": "Cofi Salaheddine", "number": 32, "pos": "D", "grid": "2:2"}}, {"player": {"id": 195071, "name": "Oussama Soukhane", "number": 47, "pos": "D", "grid": "2:1"}}, {"player": {"id": 156748, "name": "Anas Serrhat", "number": 5, "pos": "M", "grid": "3:2"}}, {"player": {"id": 337443, "name": "Amine El Msane", "number": 3, "pos": "D", "grid": "3:1"}}, {"player": {"id": 195070, "name": "Amine Souane", "number": 14, "pos": "M", "grid": "4:3"}}, {"player": {"id": 193187, "name": "Abdessamad Mahir", "number": 8, "pos": "M", "grid": "4:2"}}, {"player": {"id": 36694, "name": "Lamine Diakit\u00e9", "number": 11, "pos": "M", "grid": "4:1"}}, {"player": {"id": 184004, "name": "Ali El Harrak", "number": 30, "pos": "M", "grid": "5:1"}}], "substitutes": [{"player": {"id": 338553, "name": "Chouaib Faidi", "number": 7, "pos": "M", "grid": null}}, {"player": {"id": 535235, "name": "Arthur Gitego", "number": 66, "pos": "F", "grid": null}}, {"player": {"id": 335773, "name": "Rachid Ghanimi", "number": 1, "pos": "G", "grid": null}}, {"player": {"id": 385701, "name": "Yassine Amhih", "number": 4, "pos": "D", "grid": null}}, {"player": {"id": 410407, "name": "Anas El Makkaoui", "number": 16, "pos": "M", "grid": null}}, {"player": {"id": 143835, "name": "Hamza Moujahid", "number": 27, "pos": "M", "grid": null}}, {"player": {"id": 294298, "name": "Ismail Moutaraji", "number": 18, "pos": "M", "grid": null}}, {"player": {"id": 303520, "name": "Oussama Raoui", "number": 26, "pos": "M", "grid": null}}, {"player": {"id": 535190, "name": "Soufiane Et Tazi", "number": 49, "pos": "M", "grid": null}}], "coach": {"id": 27183, "name": "Said Chiba", "photo": "https://media.api-sports.io/football/coachs/27183.png"}}, {"team": {"id": 964, "name": "Difaa EL Jadida", "logo": "https://media.api-sports.io/football/teams/964.png", "colors": {"player": {"primary": "ccffff", "number": "333366", "border": "ccffff"}, "goalkeeper": {"primary": "000000", "number": "ffffff", "border": "000000"}}}, "formation": "3-4-3", "startXI": [{"player": {"id": 8630, "name": "Babacar Niasse", "number": 30, "pos": "G", "grid": "1:1"}}, {"player": {"id": 482839, "name": "Abdoulaye Sanogo", "number": 5, "pos": "D", "grid": "2:3"}}, {"player": {"id": 267995, "name": "Mohamed Bentarcha", "number": 14, "pos": "D", "grid": "2:2"}}, {"player": {"id": 535289, "name": "Hamza Malki", "number": 3, "pos": "D", "grid": "2:1"}}, {"player": {"id": 535238, "name": "Zakaria Oubraim", "number": 24, "pos": "D", "grid": "3:4"}}, {"player": {"id": 271786, "name": "Youssef Michte", "number": 88, "pos": "M", "grid": "3:3"}}, {"player": {"id": 435557, "name": "Brahim El Idrissi Bouzidi", "number": 6, "pos": "M", "grid": "3:2"}}, {"player": {"id": 485817, "name": "Soufiane Abaaziz", "number": 23, "pos": "D", "grid": "3:1"}}, {"player": {"id": 535210, "name": "Mouad Mouchtanim", "number": 10, "pos": "M", "grid": "4:3"}}, {"player": {"id": 535208, "name": "Abderrazak Ennakouss", "number": 17, "pos": "F", "grid": "4:2"}}, {"player": {"id": 535209, "name": "Abdallah Ziani", "number": 77, "pos": "M", "grid": "4:1"}}], "substitutes": [{"player": {"id": null, "name": "Achraf El Idrissi", "number": 99, "pos": "M", "grid": null}}, {"player": {"id": 535207, "name": "Romuald Dacosta", "number": 80, "pos": "F", "grid": null}}, {"player": {"id": 590902, "name": "Ayoub Ait Wahmane", "number": 16, "pos": "G", "grid": null}}, {"player": {"id": 590903, "name": "Oussama Benchchaoui", "number": 2, "pos": "D", "grid": null}}, {"player": {"id": 636631, "name": "Aymen Riyane", "number": 13, "pos": "D", "grid": null}}, {"player": {"id": null, "name": "Hiudaifa Jamaane", "number": 19, "pos": "M", "grid": null}}, {"player": {"id": 535237, "name": "Mohamed Hilali", "number": 21, "pos": "M", "grid": null}}, {"player": {"id": 568697, "name": "Imad Sabik", "number": 7, "pos": "F", "grid": null}}, {"player": {"id": null, "name": "Anass Mostakime", "number": 12, "pos": null, "grid": null}}], "coach": {"id": 27176, "name": "Miguel Garcia Lopes de Almeida Rui", "photo": "https://media.api-sports.io/football/coachs/27176.png"}}], "statistics": [], "players": []}]}, "timestamp": "2026-06-08T18:09:37.359889"}